smoothcode_auth/__init__.py
smoothcode_auth/auth.py
smoothcode_auth/utils.py
smoothcode_auth-0.0.4.dist-info/LICENSE
smoothcode_auth-0.0.4.dist-info/WHEEL
smoothcode_auth-0.0.4.dist-info/METADATA
smoothcode_auth-0.0.4.dist-info/RECORD
