Metadata-Version: 2.1
Name: smoothcode_auth
Version: 0.0.4
Summary: Python Auth Library that exposes utility functions to authenticate SmoothCode requests
Home-page: https://github.com/Smooth-Code-IO/smoothcode-auth-python
Author: SmoothCode
Author-email: hello@smoothcode.io
Classifier: License :: OSI Approved :: MIT License
